fastapi_buzz/__init__.py
fastapi_buzz/base.py
fastapi_buzz/py.typed
fastapi_buzz-0.1.0.dist-info/METADATA
fastapi_buzz-0.1.0.dist-info/WHEEL
fastapi_buzz-0.1.0.dist-info/licenses/LICENSE.md
fastapi_buzz-0.1.0.dist-info/RECORD
