Metadata-Version: 2.4
Name: fastapi-buzz
Version: 0.1.0
Summary: Extra bindings on py-buzz specifically for fastapi apps
Project-URL: homepage, https://github.com/dusktreader/fastapi-buzz
Project-URL: source, https://github.com/dusktreader/fastapi-buzz
Project-URL: changelog, https://github.com/dusktreader/fastapi-buzz/blob/main/CHANGELOG.md
Author-email: Tucker Beck <tucker.beck@gmail.com>
License-File: LICENSE.md
Requires-Python: >=3.10
Requires-Dist: fastapi<1.0,>=0.100.0
Requires-Dist: py-buzz~=7.0
